MANIFEST.in
README.rst
setup.py
collective/__init__.py
collective.filteredlocking.egg-info/PKG-INFO
collective.filteredlocking.egg-info/SOURCES.txt
collective.filteredlocking.egg-info/dependency_links.txt
collective.filteredlocking.egg-info/entry_points.txt
collective.filteredlocking.egg-info/namespace_packages.txt
collective.filteredlocking.egg-info/not-zip-safe
collective.filteredlocking.egg-info/requires.txt
collective.filteredlocking.egg-info/top_level.txt
collective/filteredlocking/__init__.py
collective/filteredlocking/config.py
collective/filteredlocking/configure.zcml
collective/filteredlocking/lockable.py
collective/filteredlocking/overrides.zcml
collective/filteredlocking/testing.py
collective/filteredlocking/tests.py
docs/HISTORY.rst